{
  " ñe": 376,
  "et ": 277,
  "ene": 231,
  "a a": 217,
  "ñeñ": 211,
  "eñt": 208,
  "ch ": 190,
  "net": 180,
  "all": 169,
  "en ": 168,
  " ye": 167,
  " am": 163,
  "uen": 162,
  "t ̃": 161,
  "ech": 160,
  " po": 155,
  "hue": 147,
  "pa ": 146,
  "ama": 144,
  " at": 143,
  "ohu": 141,
  " al": 141,
  "err": 136,
  "a t": 136,
  "e ñ": 134,
  "che": 130,
  "ha ": 128,
  "ma ": 128,
  "ñt ": 127,
  " ña": 125,
  "̃a ": 122,
  "ach": 121,
  "yen": 119,
  "am̃": 118,
  "ra ": 117,
  "rra": 116,
  "ñam": 109,
  " ch": 108,
  " ̃ ": 104,
  "po ": 103,
  "a y": 103,
  "ena": 102,
  " pa": 101,
  "m̃a": 99,
  "llo": 96,
  " e ": 95,
  "a ñ": 89,
  " co": 89,
  "a e": 88,
  "t ñ": 87,
  "ere": 87,
  "ñe ": 87,
  "esh": 86,
  "att": 83,
  "tt̃": 83,
  " de": 82,
  "na ": 82,
  "rec": 81,
  "t a": 80,
  "cho": 79,
  "heñ": 78,
  "der": 77,
  "ret": 77,
  "n a": 76,
  "eñe": 76,
  " t ": 76,
  "ñt̃": 75,
  "t̃e": 75,
  "sha": 75,
  "cha": 74,
  "c̈h": 74,
  "arr": 73,
  " o ": 72,
  "loh": 72,
  " ac": 72,
  "tet": 70,
  "are": 67,
  "ate": 67,
  "ñer": 66,
  "o c": 65,
  "nes": 65,
  "och": 65,
  "ets": 65,
  "a m": 64,
  "̃ a": 62,
  "coh": 62,
  "et̃": 61,
  "t̃o": 61,
  "t e": 61,
  "ten": 61,
  " añ": 60,
  "ats": 60,
  "o a": 58,
  "tse": 58,
  "añ ": 57,
  "o ñ": 55,
  "ñet": 53,
  "o p": 52,
  "a p": 51,
  " m ": 50,
  "tar": 50,
  " ts": 50,
  " er": 50,
  "ro ": 50,
  "pat": 48,
  " ec": 48,
  " es": 46,
  "hen": 46,
  "ane": 45,
  "mue": 45,
  "rr ": 45,
  "h e": 45,
  "oct": 45,
  "eñ ": 44,
  "sa ": 44,
  "t p": 43,
  "ho ": 43,
  "h a": 43,
  "os ": 43,
  "̃oc": 42,
  "t̃ ": 42,
  "ñen": 42,
  "poc": 42,
  "s ñ": 42,
  "ent": 41,
  "a c": 41,
  " ar": 41,
  "e a": 40,
  " ta": 40,
  "epa": 40,
  "e p": 40,
  "mac": 39,
  "hos": 39,
  "r p": 39,
  "ese": 38,
  "apa": 38,
  "ata": 38,
  "s a": 38,
  "ota": 37,
  "tsr": 37,
  "sro": 37,
  "sen": 36,
  "tat": 36,
  " eñ": 35,
  "rro": 35,
  "lle": 35,
  "tye": 35,
  "̃ch": 35,
  "te ": 35,
  "pue": 34,
  "tsa": 34,
  "o o": 34,
  "ey ": 34,
  "nen": 34,
  "tan": 34,
  "cte": 34,
  "t̃a": 34,
  "cma": 34,
  "h c": 33,
  "e c": 33,
  "eño": 32,
  " na": 31,
  "̃pa": 31,
  "yes": 31,
  "ñec": 30,
  "eña": 30,
  " yo": 30,
  "o t": 29,
  "o m": 29,
  "ñ ñ": 29,
  "es ": 29,
  "er ": 29,
  "ot̃": 29,
  "t̃p": 28,
  " or": 28,
  "a n": 28,
  "to ": 28,
  "orr": 28,
  "e t": 28,
  "n y": 28,
  "hye": 27,
  "chy": 27,
  "yec": 27,
  "pon": 26,
  "set": 26,
  "no ": 26,
  "t d": 26,
  "ame": 26,
  "ñot": 26,
  "h y": 26,
  "lpo": 25,
  "mpo": 25,
  "oc̈": 25,
  "eto": 25,
  " an": 25,
  "she": 25,
  "ye ": 25,
  "ts ": 25,
  "t̃c": 25,
  "nac": 25,
  "teñ": 25,
  "t̃t": 25,
  "ña ": 25,
  "llp": 25,
  "ñal": 24,
  "par": 24,
  " mu": 24,
  "̈ha": 24,
  "ete": 23,
  "ote": 23,
  "ana": 23,
  " ma": 23,
  "cop": 23,
  "ñ a": 23,
  "ahu": 23,
  " en": 23,
  "uel": 23,
  "op ": 22,
  "̃ec": 22,
  "ell": 22,
  "y a": 22,
  "nta": 22,
  "ora": 22,
  "añe": 22,
  "̃te": 22,
  "mar": 22,
  "ñ d": 21,
  "hua": 21,
  "aru": 21,
  "rua": 21,
  "on ": 21,
  "uas": 21,
  "as ": 21,
  "n ñ": 20,
  "uer": 20,
  "ne ": 20,
  " pe": 20,
  "tañ": 20,
  "rrt": 20,
  "tso": 20,
  "e o": 20,
  " ya": 20,
  "nte": 20,
  "ecm": 20,
  "n p": 20,
  "ec̈": 19,
  "emp": 19,
  "̃e ": 19,
  "̃ar": 19,
  "pot": 19,
  "uet": 19,
  "m e": 19,
  "ant": 19,
  " pu": 19,
  "rta": 19,
  "nan": 19,
  "̃ p": 18,
  " ño": 18,
  "ñ p": 18,
  "rre": 18,
  "ar ": 18,
  "yeñ": 18,
  "que": 18,
  "ann": 18,
  "tpa": 17,
  "̃ey": 17,
  "ta ": 17,
  "n d": 17,
  "asa": 17,
  " t̃": 17,
  " te": 17,
  "pen": 17,
  "n e": 17,
  "eno": 17,
  "p̃a": 17,
  "het": 17,
  "yey": 17,
  "an ": 16,
  "r e": 16,
  "cot": 16,
  "ida": 16,
  "le ": 16,
  " ne": 16,
  "o e": 16,
  "ñap": 16,
  "loc": 16,
  "ñoc": 15,
  "ney": 15,
  "r ñ": 15,
  "̃o ": 15,
  "ay ": 15,
  "one": 15,
  "a o": 15,
  "ses": 15,
  "̃ c": 15,
  "aye": 15,
  " ̃a": 15,
  "ll ": 15,
  "yep": 15,
  "tep": 15,
  "ser": 14,
  "ñat": 14,
  "yoc": 14,
  "hña": 14,
  "ap̃": 14,
  "rot": 14,
  "amo": 14,
  "h p": 14,
  "nar": 14,
  "men": 14,
  "chñ": 14,
  "o y": 14,
  " sh": 14,
  "llc": 14,
  "ya ": 14,
  "at̃": 14,
  "y ñ": 14,
  "amu": 14,
  "oya": 14,
  "oñ ": 14,
  "e e": 14,
  "poñ": 13,
  "eco": 13,
  "mo ": 13,
  "uep": 13,
  "eye": 13,
  "enp": 13,
  "etp": 13,
  "re ": 13,
  "her": 13,
  "hat": 13,
  "cpa": 13,
  "oñe": 13,
  "p ñ": 12,
  "erb": 12,
  "yet": 12,
  "̃ e": 12,
  "tam": 12,
  "roc": 12,
  "̃en": 12,
  "̃ap": 12,
  "eyc": 12,
  "̈ht": 12,
  "pay": 12,
  "hta": 12,
  "aci": 12,
  "yc̈": 12,
  "nam": 12,
  "acp": 12,
  "t o": 12,
  "nna": 11,
  "ern": 11,
  "yor": 11,
  "sem": 11,
  "tã": 11,
  "map": 11,
  "e n": 11,
  " c̈": 11,
  "ion": 11,
  "cio": 11,
  "so ": 11,
  "m̃p": 11,
  "aty": 11,
  "ocm": 11,
  "p̃ñ": 11,
  "o d": 11,
  "ñch": 11,
  "yay": 11,
  "ier": 10,
  "ore": 10,
  "ia ": 10,
  " ot": 10,
  " go": 10,
  " hu": 10,
  "obi": 10,
  "̃ o": 10,
  "nid": 10,
  "uni": 10,
  "r a": 10,
  "̃pe": 10,
  "das": 10,
  "gob": 10,
  "s u": 10,
  "rno": 10,
  "let": 10,
  "ãp": 10,
  " un": 10,
  "̈he": 10,
  "bie": 10,
  "hac": 10,
  "aña": 10,
  " qu": 10,
  "sho": 10,
  "rat": 9,
  "̃ña": 9,
  "ot ": 9,
  "ley": 9,
  "lem": 9,
  "̈ho": 9,
  "est": 9,
  "nt̃": 9,
  "yem": 9,
  "esa": 9,
  " ̃o": 9,
  "soc": 9,
  "lo ": 9,
  "ñoñ": 9,
  "l ñ": 9,
  "̃ y": 9,
  "̈hn": 9,
  "ua ": 9,
  "nah": 8,
  "cta": 8,
  "oñc": 8,
  "rbe": 8,
  "aco": 8,
  "neñ": 8,
  "̃p̃": 8,
  "h s": 8,
  "coñ": 8,
  "pam": 8,
  "nty": 8,
  "pe ": 8,
  "p a": 8,
  "lch": 8,
  "rrp": 8,
  " le": 8,
  "t c": 8,
  "me ": 8,
  "nay": 8,
  "por": 8,
  "hno": 8,
  "noc": 8,
  "npa": 8,
  "aqu": 8,
  "yan": 7,
  " se": 7,
  "m y": 7,
  " p̃": 7,
  "coy": 7,
  "tey": 7,
  " mo": 7,
  "nne": 7,
  "eta": 7,
  " a ": 7,
  "m̃c": 7,
  "ren": 7,
  "aya": 7,
  "san": 7,
  "̃or": 7,
  "s e": 7,
  "huo": 7,
  "̃ ñ": 7,
  " ty": 7,
  "̃an": 7,
  "m p": 7,
  "per": 7,
  "̃ye": 7,
  "enc": 7,
  "hay": 7,
  "ero": 7,
  " ̃y": 7,
  " ap": 7,
  "apr": 7,
  "m a": 6,
  "mat": 6,
  "ape": 6,
  "yom": 6,
  "tac": 6,
  "pah": 6,
  " m̃": 6,
  "hes": 6,
  "ter": 6,
  "omp": 6,
  "rom": 6,
  "rer": 6,
  "omñ": 6,
  " ̃c": 6,
  "y e": 6,
  "o n": 6,
  " ̃p": 6,
  "peñ": 6,
  "tue": 6,
  "h m": 6,
  "udi": 6,
  "ues": 6,
  "tud": 6,
  "uoy": 6,
  "stu": 6,
  "̈h ": 6,
  "mña": 6,
  " ah": 6,
  "ocp": 6,
  "not": 6,
  "esc": 6,
  "n c": 6,
  "scu": 6,
  "cue": 6,
  "h t": 6,
  "dad": 6,
  "cpu": 6,
  "o g": 6,
  "n o": 6,
  "acm": 6,
  "rid": 6,
  "rañ": 6,
  "moñ": 5,
  " pr": 5,
  "hoc": 5,
  "e y": 5,
  "̃ñe": 5,
  "gan": 5,
  "h o": 5,
  "s p": 5,
  " ga": 5,
  "uam": 5,
  "a s": 5,
  " el": 5,
  "ac̈": 5,
  "pre": 5,
  "eya": 5,
  "npu": 5,
  "mne": 5,
  "ado": 5,
  "bet": 5,
  "ara": 5,
  " so": 5,
  "lca": 5,
  " vo": 5,
  "b̃a": 5,
  "ñar": 5,
  "res": 5,
  "ep̃": 5,
  "sta": 5,
  "emn": 5,
  "ñ e": 5,
  "m m": 5,
  "at ": 5,
  "har": 5,
  "tor": 5,
  "met": 5,
  "s y": 5,
  "vot": 5,
  " ̃ñ": 5,
  "̃ t": 5,
  "tte": 5,
  " as": 5,
  "sat": 5,
  "uan": 5,
  "ott": 5,
  " no": 5,
  "llt": 5,
  "pal": 5,
  "yam": 5,
  "ori": 4,
  "dia": 4,
  "ran": 4,
  " aq": 4,
  "emo": 4,
  "tap": 4,
  "ñ y": 4,
  "t y": 4,
  "sar": 4,
  "p̃s": 4,
  "he ": 4,
  "uec": 4,
  "car": 4,
  "ber": 4,
  "tad": 4,
  "pan": 4,
  "yot": 4,
  "nma": 4,
  "hap": 4,
  "onm": 4,
  "ase": 4,
  " ̃e": 4,
  "t q": 4,
  "t s": 4,
  "ñ c": 4,
  "rpa": 4,
  "pes": 4,
  "l y": 4,
  "hon": 4,
  "paq": 4,
  "ont": 4,
  "ñ o": 4,
  "ety": 4,
  "eyo": 4,
  "csh": 4,
  "rne": 4,
  "rb̃": 4,
  "h g": 4,
  "ocs": 4,
  "han": 4,
  "sot": 4,
  "otu": 4,
  "n m": 4,
  "oco": 4,
  "ueñ": 4,
  "a d": 4,
  "ñpa": 4,
  "psh": 4,
  " ps": 4,
  "al ": 4,
  "r y": 4,
  "yap": 4,
  "r s": 4,
  "m̃i": 4,
  " ag": 4,
  "aga": 4,
  "tst": 4,
  "gap": 4,
  "epe": 4,
  "oty": 4,
  "e l": 4,
  "̃ot": 4,
  "rap": 4,
  "hoh": 4,
  " ep": 3,
  "ial": 3,
  "uto": 3,
  "cia": 3,
  "oci": 3,
  "d s": 3,
  "n t": 3,
  "cie": 3,
  "ien": 3,
  "ad ": 3,
  "uri": 3,
  "gur": 3,
  "yo ": 3,
  "egu": 3,
  "co ": 3,
  "seg": 3,
  "l p": 3,
  "s t": 3,
  " ay": 3,
  "aut": 3,
  " au": 3,
  "ca ": 3,
  "ue ": 3,
  "h ñ": 3,
  "ble": 3,
  "uat": 3,
  "mor": 3,
  "deb": 3,
  "ebe": 3,
  "arn": 3,
  "uez": 3,
  "̃ia": 3,
  "jue": 3,
  "a g": 3,
  "̃oh": 3,
  "ale": 3,
  "mte": 3,
  " mt": 3,
  "elo": 3,
  "p̃o": 3,
  "rpe": 3,
  "sor": 3,
  "ñts": 3,
  "ayo": 3,
  "reñ": 3,
  "n g": 3,
  "era": 3,
  "aso": 3,
  "cmu": 3,
  "a h": 3,
  "nch": 3,
  "sye": 3,
  "esy": 3,
  "lta": 3,
  "̃er": 3,
  "t̃u": 3,
  "̃ua": 3,
  " ju": 3,
  "ón ": 3,
  "ión": 3,
  "ció": 3,
  "̃sa": 3,
  "̃am": 3,
  "̃eñ": 3,
  "e m": 3,
  "yac": 3,
  " ̃m": 3,
  "nco": 3,
  "o h": 3,
  "mon": 3,
  "̃po": 3,
  "ela": 3,
  "ria": 3,
  "tẽ": 3,
  "ct̃": 3,
  "ato": 3,
  " tp": 3,
  "lla": 3,
  "n n": 3,
  "ner": 3,
  " sa": 3,
  "̃co": 3,
  "ñ l": 3,
  "las": 3,
  "prr": 3,
  "or ": 3,
  "pro": 3,
  "des": 3,
  "oye": 3,
  "ño ": 3,
  "ade": 3,
  "̈hr": 3,
  "eso": 3,
  "yer": 3,
  "̃ño": 3,
  "r c": 2,
  "de ": 2,
  "pap": 2,
  "cat": 2,
  "apo": 2,
  "m ñ": 2,
  " ci": 2,
  "nti": 2,
  "tif": 2,
  "ifi": 2,
  "fic": 2,
  "ico": 2,
  "uap": 2,
  "t n": 2,
  "sam": 2,
  "amb": 2,
  "mbl": 2,
  "lea": 2,
  "ea ": 2,
  " ge": 2,
  "gen": 2,
  "lqu": 2,
  "quë": 2,
  "ral": 2,
  "s n": 2,
  "tpo": 2,
  "ntu": 2,
  "̃rr": 2,
  "rac": 2,
  "mañ": 2,
  " to": 2,
  "ñan": 2,
  "tch": 2,
  "a q": 2,
  "mer": 2,
  "̃ep": 2,
  "cos": 2,
  "osh": 2,
  "hro": 2,
  "hch": 2,
  "chc": 2,
  "ben": 2,
  "̃añ": 2,
  "r t": 2,
  "s o": 2,
  "rte": 2,
  "̃ h": 2,
  "soy": 2,
  "y y": 2,
  "̃ps": 2,
  "psa": 2,
  "añc": 2,
  "s m": 2,
  "ezp": 2,
  "dio": 2,
  "zpa": 2,
  "sto": 2,
  "nom": 2,
  "n s": 2,
  "̃ac": 2,
  "obl": 2,
  "ñac": 2,
  "ari": 2,
  "ima": 2,
  "lte": 2,
  "pri": 2,
  " be": 2,
  "ayy": 2,
  "yye": 2,
  "sas": 2,
  "se ": 2,
  "sal": 2,
  "ler": 2,
  "dot": 2,
  "e s": 2,
  " st": 2,
  "do ": 2,
  "t t": 2,
  "̃ta": 2,
  "nat": 2,
  "m̃r": 2,
  "̃re": 2,
  "som": 2,
  "ica": 2,
  "ocr": 2,
  "ome": 2,
  "ano": 2,
  "m c": 2,
  "ami": 2,
  "señ": 2,
  "yar": 2,
  "r r": 2,
  "̃ d": 2,
  " re": 2,
  "nye": 2,
  "esp": 2,
  "spa": 2,
  "uey": 2,
  "lco": 2,
  "apc": 2,
  "sna": 2,
  "tsn": 2,
  "art": 2,
  "pc̈": 2,
  "̃se": 2,
  "̃at": 2,
  "cac": 2,
  "hop": 2,
  "̃ m": 2,
  "aca": 2,
  "vac": 2,
  " va": 2,
  "m s": 2,
  "ste": 2,
  "mes": 2,
  "rep": 2,
  "oña": 2,
  "a v": 2,
  "añp": 2,
  "eñp": 2,
  "̃mu": 2,
  "e v": 2,
  " tt": 2,
  "tts": 2,
  "dic": 2,
  "sah": 2,
  "o q": 2,
  "nca": 2,
  "epu": 2,
  "rim": 2,
  "ñ s": 1,
  "ñ t": 1,
  "nse": 1,
  "ans": 1,
  "can": 1,
  "alc": 1,
  "̃et": 1,
  " si": 1,
  "y l": 1,
  "sin": 1,
  "ind": 1,
  "uañ": 1,
  "h h": 1,
  "ñep": 1,
  "les": 1,
  "ehu": 1,
  "ñeh": 1,
  "ndi": 1,
  "pas": 1,
  "apu": 1,
  "l t": 1,
  "n h": 1,
  " ho": 1,
  "hor": 1,
  "ras": 1,
  "cci": 1,
  "ecc": 1,
  "̃oñ": 1,
  "lap": 1,
  "lec": 1,
  "epr": 1,
  "ele": 1,
  "̃ v": 1,
  "t v": 1,
  "sap": 1,
  "opa": 1,
  "s g": 1,
  "rar": 1,
  "h v": 1,
  "ñl ": 1,
  "eñl": 1,
  "̃tp": 1,
  "ẽt": 1,
  "sht": 1,
  " ̃s": 1,
  "am ": 1,
  "fo ": 1,
  "̃ma": 1,
  "iot": 1,
  "adi": 1,
  "rad": 1,
  " ra": 1,
  "t r": 1,
  "tfo": 1,
  "atf": 1,
  "pye": 1,
  "apy": 1,
  "m r": 1,
  " ny": 1,
  "̃n ": 1,
  "ẽn": 1,
  " rr": 1,
  "rrn": 1,
  "beñ": 1,
  " et": 1,
  "hre": 1,
  "rna": 1,
  " nm": 1,
  "ias": 1,
  "lia": 1,
  "ili": 1,
  "mil": 1,
  "nme": 1,
  "fam": 1,
  " fa": 1,
  "n f": 1,
  "p o": 1,
  "cll": 1,
  " fe": 1,
  "pac": 1,
  "s h": 1,
  "poy": 1,
  "lar": 1,
  "oll": 1,
  "rol": 1,
  "dem": 1,
  "hoy": 1,
  "moc": 1,
  "oyo": 1,
  "crá": 1,
  "rát": 1,
  "áti": 1,
  "tic": 1,
  "hai": 1,
  "ai ": 1,
  "l a": 1,
  "man": 1,
  "i ñ": 1,
  "acu": 1,
  "cua": 1,
  "eme": 1,
  "hem": 1,
  "̃ty": 1,
  "lop": 1,
  "̃pu": 1,
  "̃ n": 1,
  "r o": 1,
  "ãr": 1,
  "opn": 1,
  "pna": 1,
  "cob": 1,
  "obr": 1,
  "bra": 1,
  "iac": 1,
  "í y": 1,
  "lí ": 1,
  "alí": 1,
  "sec": 1,
  "ope": 1,
  "die": 1,
  "tos": 1,
  "cto": 1,
  "ect": 1,
  "eny": 1,
  "ose": 1,
  "̃os": 1,
  "be ": 1,
  "roy": 1,
  "h b": 1,
  "mia": 1,
  "ton": 1,
  " ob": 1,
  "sep": 1,
  "pet": 1,
  "bli": 1,
  "ecp": 1,
  "lig": 1,
  "ht̃": 1,
  "op̃": 1,
  "m̃ñ": 1,
  "om ": 1,
  "iga": 1,
  "gat": 1,
  "ẽ ": 1,
  "ios": 1,
  "a j": 1,
  "o j": 1,
  "zes": 1,
  "eze": 1,
  "n j": 1,
  "anc": 1,
  "hte": 1,
  " b̃": 1,
  "ñ b": 1,
  "tta": 1,
  "rma": 1,
  "rrm": 1,
  "uci": 1,
  "tuc": 1,
  "mas": 1,
  "itu": 1,
  "tit": 1,
  "sti": 1,
  "nst": 1,
  "ons": 1,
  "con": 1,
  "o l": 1,
  "rah": 1,
  " av": 1,
  "ava": 1,
  "ema": 1,
  "rob": 1,
  "n l": 1,
  "e b": 1,
  "mrr": 1,
  " mr": 1,
  "rp̃": 1,
  "omu": 1,
  "pom": 1,
  "ñey": 1,
  "ray": 1,
  "loñ": 1,
  "ich": 1,
  "̃ic": 1,
  "crr": 1,
  "van": 1,
  "anz": 1,
  "hañ": 1,
  "cch": 1,
  "occ": 1,
  "uoc": 1,
  "nza": 1,
  "lam": 1,
  "ual": 1,
  "uar": 1,
  "lua": 1,
  "llu": 1,
  "zad": 1,
  "y o": 1,
  "dos": 1,
  "p s": 1,
  "ash": 1,
  "nas": 1,
  "y c": 1,
  "ñte": 1,
  "ñtp": 1,
  " me": 1,
  "sño": 1,
  "tsñ": 1,
  " tu": 1,
  "p y": 1,
  "etc": 1,
  "tõ": 1,
  "õr": 1,
  "coc": 1,
  "hne": 1,
  "erp": 1,
  "y p": 1,
  "y n": 1,
  "nt ": 1,
  "ëne": 1,
  "uën": 1,
  " lq": 1,
  "rog": 1,
  "̃ q": 1,
  "bro": 1,
  "ibr": 1,
  "lib": 1,
  " li": 1,
  "ssa": 1,
  "ass": 1,
  "aro": 1,
  "mts": 1,
  "omt": 1,
  "tno": 1,
  " tn": 1,
  "l q": 1,
  "m l": 1,
  "atr": 1,
  "tr̃": 1,
  "r̃r": 1,
  "̃ra": 1,
  "ett": 1,
  "rña": 1,
  "arñ": 1,
  "rt̃": 1,
  "ños": 1,
  "emu": 1,
  "cht": 1,
  "ap ": 1,
  "eñc": 1,
  "nañ": 1,
  "ona": 1,
  "rpo": 1,
  "rye": 1,
  "rry": 1,
  "atp": 1,
  "tua": 1,
  "ogr": 1,
  "gre": 1,
  "ñtc": 1,
  "nor": 1,
  "lac": 1,
  " ll": 1,
  "a l": 1,
  "pel": 1,
  "hca": 1,
  "̃ll": 1,
  "p̃l": 1,
  "̃de": 1,
  " ̃d": 1,
  "ët ": 1,
  "uët": 1,
  "llq": 1,
  " la": 1,
  "̈hc": 1,
  "l d": 1,
  "̃as": 1,
  "bre": 1,
  "mbr": 1,
  "emb": 1,
  "iem": 1,
  "ici": 1,
  " di": 1,
  "e d": 1,
  "fec": 1,
  "ñ f": 1,
  "acl": 1
}