{"yua":11,"uak":11,"t t":11,"tua":11,"d t":11,"gon":11,"l b":11," su":11,"zis":11," we":11,"aox":11,"deb":11,"oud":11,"gha":11,"shu":11,"d h":12," nt":12,"f x":12,"ub ":12,"et ":12," ch":12,"t b":12,"d m":12,"x x":12," ro":12,"d p":12," hl":13,"s b":13,"zho":13,"al ":13,"lb ":13,"eut":13,"d b":13," bo":13,"b k":13,"lan":13,"s l":13,"uaf":13,"s m":13,"mol":14,"deu":14,"dex":14,"k z":14,"due":14," be":14,"ak ":14,"f s":14,"iao":14,"s x":14,"f l":14,"hik":14,"d g":14,"x i":14,"s y":14,"x b":14," fu":14,"ros":15,"f b":15," gh":15,"k n":15,"pin":15,"end":15,"aid":15,"gt ":15,"zos":15,"d l":15,"hab":16," bi":16," mo":16," za":16,"uas":16,"aik":16,"x h":16,"gai":16,"f t":16,"d y":16,"aos":16,"ngt":16," zu":16,"el ":17,"t h":17,"t r":17," ib":17,"hou":17,"dus":17,"und":17,"hun":17,"nzh":18,"t y":18," pi":18,"hif":18,"l d":18,"dax":19,"gua":19,"hed":19,"eb ":19,"hef":19,"b l":19,"d j":19,"b t":19,"s t":19,"las":19,"ngx":20,"gx ":20,"x t":20,"x m":20,"b b":21,"b s":21,"aof":21," li":21,"x s":21,"xin":21,"x y":22," nz":22," di":22," ga":22,"bao":23," zo":23,"zif":23,"x l":23,"ait":23,"ot ":23," ju":23,"jua":23," dl":23," ba":23," kh":23,"aod":23,"l m":24," qi":24,"hue":24,"x g":24,"ren":24," xi":24,"s s":25,"aib":25," la":25,"d d":25,"sha":26,"jai":26,"xan":26,"hua":26,"b y":26,"gf ":26," ha":26," id":27,"af ":27,"uk ":27,"t s":27," xa":27,"b c":27," re":28,"nad":28,"lol":28,"f d":28,"dou":28,"is ":29,"nya":29,"ex ":29,"ous":29,"enf":29,"hen":30,"zhu":30,"nil":30,"yin":30,"rou":30,"out":30," hu":31,"bua":31,"you":31,"od ":32,"b h":32,"ged":32,"hai":32," ya":32,"t g":32,"ngf":32," bu":33,"lob":33,"ik ":33,"shi":33," ji":33," ny":34,"of ":34,"heu":34," gu":35,"s z":35,"zha":35," da":35," ja":35,"uad":35,"x c":35,"f h":36,"han":36,"ndo":36,"oux":37,"f y":37," du":37,"x j":37,"ud ":38,"gox":38,"nd ":38," na":38,"il ":38," ua":38,"b g":39,"len":39,"s n":40,"f z":40,"hox":40,"uef":40,"d s":41," ge":41,"x d":42,"ngb":42,"gb ":42,"dro":42," ne":43," le":43,"inx":43,"nen":43,"das":43,"euf":44,"zhe":45,"dol":45," yo":45,"f g":45," dr":45,"d z":46,"ut ":46,"enb":46,"uab":46,"ix ":46,"yao":46," de":46,"nda":47," zi":48,"ong":49,"t z":49,"l n":50,"aob":50," yi":51,"x z":51,"ux ":51,"b z":52," ho":52,"t n":52,"us ":53,"b d":53,"ed ":53,"she":53," go":54,"inf":55,"gd ":56,"t l":57,"ngd":57,"f n":59," lo":60,"nb ":61,"hit":61,"enx":62," cu":62,"id ":62,"s d":63,"ib ":64,"dos":64,"uf ":65,"b n":66,"ad ":68,"mua":69,"cua":70,"uax":70," mu":71,"d n":72,"if ":72,"ef ":73,"as ":78," ta":78,"tab":78,"zhi":84,"nf ":84,"x n":85,"t d":86," nd":91,"ob ":92,"ol ":100,"nx ":104,"ax ":111,"os ":112," do":113,"ox ":113,"uat":117,"nit":122,"ang":126," sh":127,"at ":133,"ab ":149," ni":154," zh":189,"it ":215}