{
  "ya ": 198,
  "huë": 195,
  "hua": 188,
  "a n": 167,
  " hu": 164,
  " ya": 151,
  "ina": 138,
  "a h": 138,
  "na ": 124,
  "so ": 123,
  " ni": 116,
  "chi": 115,
  "uër": 108,
  "hin": 106,
  " no": 106,
  "pi ": 97,
  "uë ": 97,
  " co": 94,
  "aso": 93,
  "rin": 90,
  "quë": 90,
  " na": 87,
  "a i": 86,
  "aca": 85,
  "ach": 80,
  "ëri": 80,
  "api": 78,
  "ua ": 77,
  " in": 70,
  "o y": 70,
  "in ": 69,
  "cas": 65,
  "poa": 64,
  "ahu": 63,
  " sa": 63,
  "opi": 63,
  "ohu": 62,
  "co ": 61,
  "npo": 61,
  "noy": 61,
  "oya": 61,
  "ëhu": 59,
  "a c": 57,
  "ipi": 55,
  "a y": 55,
  "an ": 54,
  " pi": 53,
  "nan": 53,
  " ma": 52,
  "a a": 52,
  "inp": 52,
  " pa": 50,
  "sha": 50,
  " a ": 49,
  "ta ": 49,
  "nap": 47,
  "ana": 47,
  "ha ": 46,
  "no ": 46,
  "uac": 45,
  "a p": 45,
  " ip": 45,
  "nhu": 42,
  "arë": 42,
  " an": 42,
  "inh": 41,
  "nin": 41,
  " qu": 40,
  "o n": 40,
  "oa ": 39,
  "iya": 38,
  "yap": 38,
  "mar": 38,
  "pin": 38,
  "tër": 37,
  "ëra": 37,
  "ë n": 37,
  "piy": 36,
  "uën": 35,
  "n n": 35,
  " të": 35,
  "nto": 34,
  "i p": 34,
  "o m": 34,
  "pir": 34,
  "iso": 34,
  "n a": 33,
  "toh": 32,
  "cat": 32,
  "sa ": 32,
  "nta": 32,
  "ant": 32,
  "o s": 32,
  "tac": 31,
  "ata": 31,
  "ran": 31,
  "ita": 31,
  "nis": 31,
  "ish": 30,
  "ërë": 29,
  "rë ": 29,
  "ma ": 29,
  "ë c": 28,
  "ais": 28,
  "i n": 28,
  "top": 27,
  "pit": 27,
  "a s": 26,
  "aqu": 26,
  "ton": 26,
  "cai": 26,
  "cop": 25,
  "irn": 25,
  "rno": 25,
  "yon": 25,
  "o t": 25,
  "oro": 24,
  "tëh": 24,
  "ito": 23,
  "rëh": 23,
  "ën ": 23,
  "atë": 23,
  "ë a": 22,
  "uan": 22,
  "nën": 22,
  "nac": 21,
  " ca": 21,
  "ont": 21,
  "hui": 21,
  " to": 21,
  "sac": 21,
  "nit": 20,
  "ins": 20,
  "ro ": 20,
  "a t": 20,
  "ani": 20,
  "ato": 19,
  "pac": 19,
  "apo": 19,
  "n q": 19,
  "i s": 19,
  "nqu": 19,
  "pah": 18,
  " sh": 18,
  "ino": 18,
  "on ": 18,
  "int": 18,
  "i c": 18,
  "ni ": 18,
  "iri": 17,
  "n c": 17,
  "tah": 17,
  "oas": 17,
  "qui": 17,
  "ini": 17,
  "n i": 16,
  "par": 16,
  "ica": 16,
  "nch": 15,
  "a q": 15,
  "ona": 15,
  "ënt": 15,
  "noh": 15,
  "ihu": 15,
  "ëqu": 15,
  "n p": 14,
  "o p": 14,
  "anë": 14,
  "ri ": 14,
  "ënp": 14,
  "nip": 14,
  "ëca": 14,
  " ch": 14,
  "ënë": 14,
  "ama": 14,
  "coi": 14,
  "naq": 13,
  "itë": 13,
  "a m": 13,
  "ari": 13,
  "ë p": 13,
  "inc": 13,
  " am": 13,
  "tëq": 13,
  "i t": 13,
  "san": 12,
  "pia": 12,
  "ian": 12,
  "oin": 12,
  "niy": 12,
  "iyo": 12,
  "npa": 12,
  "shi": 12,
  "hi ": 12,
  "ra ": 12,
  "uat": 12,
  "n y": 12,
  "uir": 12,
  "ë y": 12,
  "onq": 12,
  "oso": 12,
  "soh": 12,
  "i y": 12,
  " ta": 11,
  "onp": 11,
  "cha": 11,
  "npi": 11,
  "nso": 11,
  "nor": 11,
  "tin": 11,
  "uëc": 11,
  "ntë": 11,
  "o a": 11,
  "ain": 11,
  " yo": 11,
  "nat": 11,
  "cac": 10,
  "i a": 10,
  "i i": 10,
  "pa ": 10,
  "hac": 10,
  "o i": 10,
  "nos": 10,
  "sor": 10,
  "oca": 10,
  "nëh": 9,
  "map": 9,
  "apa": 9,
  "ima": 9,
  "tot": 9,
  "hit": 9,
  "non": 9,
  "pat": 9,
  "nti": 9,
  "o c": 9,
  " ac": 9,
  " pë": 9,
  "tën": 8,
  "pop": 8,
  "ara": 8,
  "rëc": 8,
  "n h": 8,
  "ota": 8,
  "nsh": 8,
  "art": 8,
  "rti": 8,
  "ti ": 8,
  "son": 8,
  "o h": 8,
  " po": 8,
  "och": 8,
  "ano": 8,
  "aco": 8,
  "uëm": 8,
  "ëma": 8,
  "iin": 7,
  "iqu": 7,
  "uah": 7,
  "uar": 7,
  "aro": 7,
  "uët": 7,
  "pih": 7,
  " es": 7,
  "esc": 7,
  "scu": 7,
  "cue": 7,
  "uel": 7,
  "ela": 7,
  "ash": 7,
  "anp": 7,
  "roc": 7,
  "poc": 7,
  "ira": 7,
  "i h": 7,
  "ori": 7,
  "pën": 7,
  "uëa": 7,
  "ë t": 6,
  "uëi": 6,
  "ëin": 6,
  "uas": 6,
  "rës": 6,
  "uay": 6,
  "ayo": 6,
  "asa": 6,
  "nah": 6,
  "n s": 6,
  " im": 6,
  "ëch": 6,
  "nas": 6,
  "ëtë": 6,
  "a e": 6,
  "ca ": 6,
  "uai": 6,
  "uic": 6,
  "ëa ": 6,
  "uit": 5,
  "isë": 5,
  " ap": 5,
  "ësi": 5
}
