{
  "aće": 8,
  "měn": 8,
  "oda": 8,
  "la ": 8,
  "łuš": 8,
  "oso": 8,
  "swě": 8,
  "e r": 8,
  "e m": 8,
  "ž s": 8,
  "ste": 8,
  "soc": 8,
  "hło": 8,
  "oci": 8,
  "łos": 8,
  "kel": 8,
  "ojo": 8,
  "jo ": 8,
  "elž": 8,
  "cia": 8,
  "ial": 8,
  "imi": 8,
  "po ": 8,
  "ći ": 8,
  "lž ": 8,
  "tup": 8,
  "oće": 8,
  "isł": 8,
  "źěl": 8,
  "ace": 8,
  "odu": 9,
  "nan": 9,
  "sob": 9,
  "els": 9,
  " te": 9,
  "źe ": 9,
  "by ": 9,
  "low": 9,
  "pod": 9,
  "rom": 9,
  "atn": 9,
  "ćiw": 9,
  "wšě": 9,
  "rež": 9,
  "zna": 9,
  "wop": 9,
  "w a": 9,
  "słu": 9,
  " kó": 9,
  "oma": 9,
  "and": 9,
  "ach": 9,
  "nic": 9,
  "own": 9,
  "cho": 9,
  "ški": 9,
  "tej": 9,
  "jem": 9,
  "m p": 9,
  "wne": 9,
  "om ": 9,
  "bje": 9,
  "mad": 9,
  "opr": 9,
  " z ": 9,
  "akł": 9,
  "kła": 9,
  "sto": 9,
  "stu": 9,
  "sći": 9,
  "run": 9,
  "ład": 9,
  "im ": 9,
  "u z": 9,
  "zhr": 9,
  "jic": 9,
  " re": 9,
  "ž j": 9,
  " mj": 9,
  "ran": 9,
  "aln": 9,
  "nak": 10,
  "li ": 10,
  "ki ": 10,
  "dru": 10,
  "e č": 10,
  "jej": 10,
  "kit": 10,
  "i p": 10,
  "o t": 10,
  "łez": 10,
  "kra": 10,
  "emu": 10,
  "wól": 10,
  "a t": 10,
  "i a": 10,
  "wěd": 10,
  "iwa": 10,
  "dźi": 10,
  "su ": 10,
  "tow": 10,
  "šit": 10,
  "wši": 10,
  "swó": 10,
  "i w": 10,
  "wój": 10,
  "hro": 10,
  "du ": 10,
  " zh": 10,
  "ě s": 11,
  "dne": 11,
  "mě ": 11,
  "łeć": 11,
  "rje": 11,
  "a m": 11,
  " to": 11,
  " mě": 11,
  "man": 11,
  "ski": 11,
  "mu ": 11,
  "adź": 11,
  " su": 11,
  " dr": 11,
  " wš": 11,
  "tre": 11,
  "ke ": 11,
  "taj": 11,
  "źěł": 11,
  "a k": 11,
  "ćen": 11,
  "twa": 11,
  " šk": 11,
  "kej": 11,
  "m w": 12,
  "měr": 12,
  "wow": 12,
  "tat": 12,
  "y p": 12,
  "wos": 12,
  "esm": 12,
  " by": 12,
  "o d": 12,
  "m a": 12,
  "odo": 12,
  "ena": 12,
  " sp": 12,
  "žiw": 13,
  "kow": 13,
  "isk": 13,
  "pow": 13,
  " tu": 13,
  "jeh": 13,
  "eny": 13,
  "ać ": 13,
  "ako": 13,
  "u p": 13,
  "raj": 13,
  "a j": 13,
  "o j": 13,
  "i s": 13,
  "łis": 13,
  "h p": 13,
  "ez ": 14,
  "awn": 14,
  "za ": 14,
  "oje": 14,
  "ež ": 14,
  "tut": 14,
  "adn": 14,
  "a n": 14,
  "dno": 14,
  "ić ": 14,
  " čł": 14,
  "smě": 14,
  "u s": 14,
  "aja": 14,
  "ist": 14,
  "dny": 15,
  "wot": 15,
  "awa": 15,
  "čło": 15,
  " zj": 15,
  "ć a": 15,
  "jew": 15,
  "u w": 15,
  "wa ": 15,
  "am ": 15,
  "a d": 15,
  "sće": 15,
  "ćkó": 15,
  "two": 15,
  "u a": 15,
  "e d": 16,
  "ske": 16,
  "o p": 16,
  "kot": 16,
  "łow": 16,
  "mje": 16,
  "otr": 16,
  "nyc": 17,
  "nju": 17,
  " ko": 17,
  "nar": 17,
  "wać": 17,
  "rod": 17,
  "ych": 17,
  "zak": 17,
  "zje": 17,
  "a a": 17,
  "dow": 18,
  "edn": 18,
  "eje": 18,
  "e z": 18,
  "aro": 19,
  "jez": 19,
  "mi ": 19,
  "o z": 19,
  "ej ": 19,
  "ny ": 19,
  " dź": 19,
  "owj": 19,
  "eho": 20,
  "odn": 20,
  "a z": 20,
  "wan": 20,
  "ho ": 20,
  "jed": 21,
  "ost": 21,
  "jes": 21,
  "dźě": 22,
  "nos": 22,
  "o s": 23,
  "o w": 23,
  "nym": 23,
  "će ": 23,
  " st": 24,
  "dźe": 24,
  "ym ": 25,
  "nja": 27,
  "y m": 27,
  "ich": 27,
  " do": 27,
  "e s": 28,
  "woj": 28,
  "stw": 28,
  "bo ": 29,
  " ab": 29,
  "osć": 29,
  "ju ": 29,
  "e a": 30,
  "ma ": 30,
  "abo": 31,
  "ždy": 31,
  " w ": 31,
  "płe": 31,
  "e w": 32,
  "so ": 33,
  "płi": 33,
  "bod": 33,
  "sta": 34,
  "obo": 34,
  " wu": 35,
  " nj": 36,
  "óžd": 37,
  "ow ": 37,
  "dy ": 37,
  "kóž": 37,
  "a w": 38,
  "o n": 38,
  "e p": 39,
  "enj": 39,
  "ja ": 39,
  "wje": 41,
  "anj": 42,
  "owa": 43,
  " so": 43,
  "ne ": 44,
  " ma": 44,
  "ch ": 44,
  "na ": 46,
  " je": 50,
  "awo": 51,
  "a p": 51,
  " po": 53,
  "a s": 53,
  " za": 54,
  "wob": 54,
  "wo ": 56,
  "jen": 56,
  " pł": 59,
  " na": 61,
  " wo": 61,
  "swo": 62,
  " pr": 70,
  "raw": 78,
  " sw": 79,
  "pra": 84,
  " a ": 97,
  "nje": 109,
  "je ": 109
}