{
  "que": 165,
  " ca": 157,
  "ra ": 156,
  "ati": 146,
  "gue": 146,
  "nga": 135,
  "ani": 132,
  "ti ": 130,
  "a i": 124,
  "igu": 122,
  " ir": 119,
  "ue ": 116,
  "nin": 116,
  "isa": 116,
  "ina": 115,
  "sat": 114,
  "can": 108,
  "uen": 100,
  "ais": 99,
  "nta": 99,
  "ro ": 98,
  "eng": 86,
  "ant": 85,
  "ca ": 84,
  "tsi": 83,
  "te ": 81,
  "nat": 79,
  "ing": 79,
  "ira": 78,
  "aqu": 77,
  "aca": 77,
  "i i": 74,
  "aig": 74,
  "iro": 74,
  " in": 73,
  "ora": 71,
  "ara": 70,
  "iri": 70,
  " ai": 69,
  "ata": 69,
  "aro": 69,
  "ats": 69,
  "car": 67,
  " or": 66,
  " pi": 65,
  "int": 65,
  "aga": 62,
  "uer": 62,
  "ri ": 61,
  "sig": 61,
  "e c": 60,
  "mat": 60,
  "ga ": 60,
  "gai": 59,
  "a p": 57,
  "i o": 55,
  "gan": 53,
  "tag": 53,
  " ma": 52,
  "taq": 51,
  "gom": 50,
  "ite": 50,
  "gui": 48,
  "ngo": 47,
  "asi": 46,
  " te": 45,
  "ta ": 45,
  "a c": 43,
  "ong": 42,
  "e o": 41,
  " on": 41,
  "i c": 41,
  "guë": 40,
  "ero": 40,
  "agu": 40,
  "e a": 39,
  "ngu": 39,
  "mi ": 38,
  "e i": 38,
  " an": 38,
  "a o": 38,
  " pa": 38,
  "i a": 37,
  "oma": 37,
  "tai": 37,
  "i p": 37,
  "ini": 35,
  "tim": 35,
  "ni ": 34,
  "ita": 34,
  " qu": 34,
  "ome": 33,
  "uë ": 33,
  "iqu": 32,
  "ima": 32,
  "nqu": 30,
  "oca": 30,
  "iti": 30,
  "nti": 29,
  "ui ": 29,
  "i m": 28,
  "anq": 28,
  "a a": 28,
  "nar": 28,
  "ten": 27,
  "sin": 27,
  "ari": 27,
  "a t": 26,
  "mei": 26,
  "eit": 26,
  "omi": 26,
  "emi": 26,
  "san": 26,
  "ica": 26,
  "rir": 26,
  "mit": 25,
  "sit": 25,
  "o a": 25,
  "pai": 25,
  "rac": 25,
  "oba": 24,
  "air": 24,
  "imi": 23,
  "pin": 23,
  "iga": 23,
  "bir": 23,
  "qui": 22,
  "nia": 22,
  " om": 22,
  "ang": 22,
  "gar": 21,
  "ota": 21,
  "gac": 21,
  "o i": 21,
  "nts": 20,
  "tir": 20,
  "eri": 19,
  " ar": 19,
  "tin": 19,
  "mag": 19,
  "uem": 19,
  "oti": 19,
  "obi": 19,
  "eni": 18,
  " ba": 18,
  "bas": 18,
  "ito": 18,
  " it": 18,
  "quë": 18,
  "egu": 18,
  "rin": 18,
  "ate": 17,
  "ma ": 17,
  "iat": 17,
  "o o": 17,
  "ran": 17,
  "man": 17,
  "i t": 16,
  "rog": 16,
  "isi": 16,
  " ic": 15,
  "pij": 15,
  "roc": 15,
  "tar": 15,
  "e p": 15,
  "oco": 15,
  "ena": 15,
  "tis": 15,
  " po": 14,
  "iji": 14,
  "pag": 14,
  "toc": 14,
  "cot": 14,
  "iba": 14,
  "equ": 14,
  "asa": 14,
  "tac": 14,
  "a q": 14,
  "gas": 13,
  "uir": 13,
  "si ": 13,
  "nas": 13,
  "rot": 13,
  " oc": 13,
  " ob": 12,
  "pit": 12,
  "a b": 12,
  "iac": 12,
  "ipa": 12,
  "roo": 12,
  " aq": 11,
  "ntë": 11,
  "o m": 11,
  "bin": 11,
  " ig": 11,
  "ëma": 11,
  "ori": 11,
  "rob": 11,
  "ane": 11,
  " sa": 11,
  "oot": 11,
  "got": 10,
  "pic": 10,
  "águ": 10,
  "e q": 10,
  "o p": 10,
  "bac": 10,
  "caa": 10,
  " je": 10,
  "jem": 10,
  "ico": 10,
  "uëm": 10,
  "anë": 10,
  "ë a": 10,
  "ogo": 10,
  "uit": 10,
  "rom": 10,
  "ëri": 10,
  "tan": 10,
  "gob": 10,
  "mar": 10,
  "ëgo": 9,
  "cag": 9,
  "nib": 9,
  "oro": 9,
  "ábi": 9,
  "re ": 9,
  "ain": 9,
  "rai": 9,
  " im": 9,
  "mis": 9,
  "ne ": 9,
  "i j": 9,
  "a s": 9,
  "tëg": 8,
  "com": 8,
  "a j": 8,
  " co": 8,
  "uim": 8,
  "ngá": 8,
  "gáb": 8,
  "ria": 8,
  "ogó": 8,
  "në ": 8,
  "oqu": 8,
  "bat": 8,
  "jeg": 8,
  "uër": 8,
  "bai": 8,
  "ë c": 8,
  "ë i": 8,
  "ai ": 8,
  "cha": 8,
  "cat": 8,
  "era": 7,
  " ij": 7,
  "tas": 7,
  "oto": 7,
  "ibo": 7,
  "ija": 7,
  "are": 7,
  "ont": 7,
  "bag": 7,
  "jan": 7,
  "mip": 7,
  "mai": 7,
  "agá": 7,
  "ha ": 7,
  "ror": 7,
  "ino": 7,
  "rit": 7,
  "a m": 7,
  "ëmi": 6,
  "uet": 6,
  "ë o": 6,
  "oga": 6,
  "aat": 6,
  " pá": 6,
  "pág": 6,
  "opa": 6,
  "jin": 6,
  "na ": 6,
  "uib": 6,
  "ait": 6,
  "son": 6,
  "nan": 6,
  "tsa": 6,
  "sai": 6,
  "igo": 6,
  "ote": 6,
  "gói": 6,
  "óig": 6,
  "ato": 6,
  "eta": 6,
  "roj": 6,
  "oje": 6,
  "uëq": 6,
  "ëqu": 6,
  " ib": 6,
  "rag": 6
}