{
  "ور ": 118,
  " او": 104,
  "اور": 103,
  " کی": 93,
  "کے ": 87,
  " کے": 86,
  "یں ": 80,
  " کا": 73,
  "کی ": 71,
  " حق": 66,
  "ے ک": 65,
  "ایٔ": 64,
  "کا ": 63,
  "یٔے": 61,
  " کو": 60,
  "یا ": 58,
  "نے ": 58,
  "سے ": 58,
  " اس": 57,
  "ٔے ": 55,
  "میں": 52,
  "کو ": 52,
  " ہے": 52,
  " می": 51,
  "ے ا": 50,
  " ان": 48,
  "وں ": 47,
  " کر": 46,
  " ہو": 44,
  "اس ": 44,
  "ی ا": 44,
  "ر ا": 43,
  "شخص": 43,
  " شخ": 43,
  "حق ": 42,
  " سے": 41,
  " جا": 40,
  "خص ": 38,
  "ہر ": 38,
  "ام ": 36,
  "ے م": 36,
  "ں ک": 35,
  "ہیں": 35,
  " یا": 35,
  "سی ": 34,
  "ادی": 33,
  "آزا": 32,
  " آز": 32,
  "زاد": 32,
  "ص ک": 30,
  "ہ ا": 30,
  "ہے ": 29,
  "جای": 29,
  "ا ح": 29,
  "ر ش": 28,
  "ت ک": 28,
  "کہ ": 28,
  "م ک": 27,
  " پر": 27,
  "ی ک": 27,
  "ان ": 27,
  "پر ": 26,
  "۔ہر": 26,
  "دی ": 26,
  "یٔی": 26,
  "س ک": 25,
  "ا ج": 25,
  "ر م": 24,
  "ہے۔": 24,
  "ق ہ": 24,
  "ں ا": 23,
  "ی ح": 23,
  "و ا": 23,
  "ار ": 22,
  "ن ک": 22,
  "قوق": 22,
  "کسی": 22,
  "حقو": 22,
  "ری ": 22,
  "وق ": 21,
  "ے گ": 21,
  " ہی": 21,
  "ی ج": 21,
  " مع": 21,
  "سان": 20,
  " نہ": 20,
  " مل": 20,
  " حا": 20,
  "ٔی ": 20,
  " جو": 20,
  "نی ": 20,
  "کرن": 20,
  " لی": 20,
  "تی ": 20,
  "ی ت": 20,
  "نسا": 19,
  "ل ک": 19,
  " کہ": 19,
  "جو ": 19,
  "انس": 19,
  "اپن": 19,
  "ے ب": 18,
  "نہ ": 18,
  " اپ": 18,
  "یت ": 18,
  "ا ا": 18,
  "ہ ک": 18,
  " کس": 18,
  "ر ک": 18,
  "رے ": 17,
  "ے ہ": 17,
  " ای": 17,
  "می ": 17,
  "ل ہ": 17,
  "۔ ا": 17,
  "ے ل": 17,
  "ی ش": 17,
  "رنے": 17,
  "وہ ": 16,
  "حاص": 16,
  "ی م": 16,
  "معا": 16,
  "اصل": 16,
  "صل ": 16,
  "یں۔": 16,
  "ویٔ": 16,
  "نہی": 16,
  "ملک": 15,
  "ایس": 15,
  "انہ": 15,
  "ات ": 15,
  "ی ب": 15,
  "د ک": 15,
  "ی ہ": 15,
  " تع": 15,
  "کیا": 15,
  "ق ک": 15,
  "ر ہ": 14,
  "ا م": 14,
  "دہ ": 14,
  " من": 14,
  " بن": 14,
  " قو": 14,
  "ے ج": 14,
  "یہ ": 14,
  "ں م": 14,
  "اشر": 14,
  "مل ": 14,
  " دو": 14,
  "عاش": 14,
  "قوم": 14,
  "ر ب": 13,
  "انی": 13,
  "وام": 13,
  "قوا": 13,
  "اقو": 13,
  "لیٔ": 13,
  "دار": 13,
  " وہ": 13,
  " و ": 13,
  " عا": 13,
  "ی س": 13,
  "بر ": 13,
  "علا": 13,
  "اد ": 12,
  "ہ م": 12,
  "و ت": 12,
  "ر ن": 12,
  " جس": 12,
  "ے۔ہ": 12,
  "ے، ": 12,
  "انو": 12,
  " دی": 12,
  "گی ": 12,
  "لیم": 12,
  "یوں": 12,
  " قا": 12,
  " یہ": 12,
  "دوس": 11,
  "ے۔ ": 11,
  "ا ہ": 11,
  "تعل": 11,
  "یم ": 11,
  "ر پ": 11,
  "جس ": 11,
  "ریق": 11,
  "ے ح": 11,
  " اق": 11,
  "نیا": 11,
  "لک ": 11,
  " گی": 11,
  "ین ": 10,
  "یاد": 10,
  " مس": 10,
  "لاق": 10,
  "، ا": 10,
  "ی ن": 10,
  "پنے": 10,
  "وری": 10,
  "م ا": 10,
  " با": 10,
  "علی": 10,
  "یر ": 10,
  "ی، ": 10,
  "انے": 10,
  "ون ": 10,
  "ن ا": 10,
  "ر ع": 10,
  " بر": 10,
  "ی آ": 10,
  "ر ح": 10,
  " رک": 10,
  "ے پ": 10,
  "کر ": 10,
  "گا۔": 10,
  " پی": 9,
  "سب ": 9,
  " گا": 9,
  "نا ": 9,
  " پو": 9,
  "یسے": 9,
  "رای": 9,
  " مر": 9,
  "اری": 9,
  "قان": 9,
  "نون": 9,
  " مم": 9,
  "ندگ": 9,
  " اع": 9,
  "دگی": 9,
  "ہ و": 9,
  " ہر": 9,
  "ر س": 9,
  " چا": 9,
  "خلا": 9,
  "ا پ": 9,
  "ق ح": 9,
  " بھ": 9,
  "س م": 9,
  " شا": 9,
  "ہوگ": 9,
  "ے خ": 9,
  "وسر": 9,
  "رتی": 9,
  "ومی": 9,
  " بی": 9,
  "رکھ": 9,
  " مت": 8,
  "کوی": 8,
  "ر آ": 8,
  "پور": 8,
  "اف ": 8,
  " مح": 8,
  "ے س": 8,
  "ہوں": 8,
  "نکہ": 8,
  "ونک": 8,
  "ت ا": 8,
  " طر": 8,
  "ے ع": 8,
  "یٔد": 8,
  "د ا": 8,
  "ال ": 8,
  "ں۔ ": 8,
  "م م": 8,
  "اں ": 8,
  " مق": 8,
  "غیر": 8,
  "پنی": 8,
  " ام": 8,
  "ں، ": 8,
  "من ": 8,
  "ہو ": 8,
  "ریع": 8,
  "و ک": 8,
  "ذری": 8,
  " ذر": 8,
  "عام": 8,
  "، م": 8,
  "دان": 8,
  "ادا": 8,
  "اعل": 8,
  "مام": 8,
  "تما": 8,
  " عل": 8,
  "دیو": 8,
  "بھی": 8,
  "ھی ": 8,
  "بنی": 8,
  "ے ی": 8,
  "ا ک": 8,
  "اوی": 7,
  "ل م": 7,
  " زن": 7,
  "یاس": 7,
  "لان": 7,
  "عمل": 7,
  " عم": 7,
  "ت م": 7,
  " بچ": 7
}